deepblocks/__init__.py
deepblocks/version.py
deepblocks/activation/FReLU.py
deepblocks/activation/__init__.py
deepblocks/layer/ConvMixerLayer.py
deepblocks/layer/DenseBlock.py
deepblocks/layer/FlipConv2d.py
deepblocks/layer/MultiHeadAttention.py
deepblocks/layer/SE.py
deepblocks/layer/__init__.py
deepblocks/loss/AUCLoss.py
deepblocks/loss/FocalLoss.py
deepblocks/loss/KLDivLoss.py
deepblocks/loss/_Loss.py
deepblocks/loss/__init__.py
deepblocks/network/ConvMixer.py
deepblocks/network/ICTNet.py
deepblocks/network/UNet.py
deepblocks/network/__init__.py
deepblocks/optim/SAM.py
deepblocks/optim/__init__.py
deepblocks/regularizer/AntiCorrelation.py
deepblocks/regularizer/__init__.py
deepblocks/ssl/BarlowTwin.py
deepblocks/ssl/Dino.py
deepblocks/ssl/__init__.py
deepblocks-0.1.13.dist-info/LICENSE
deepblocks-0.1.13.dist-info/METADATA
deepblocks-0.1.13.dist-info/WHEEL
deepblocks-0.1.13.dist-info/top_level.txt
deepblocks-0.1.13.dist-info/RECORD
