Metadata-Version: 2.1
Name: deepblocks
Version: 0.1.13
Summary: Useful PyTorch Layers
Home-page: https://github.com/blurry-mood/Deep-Learning-Blocks
Author: Ayoub Assis
Author-email: assis.ayoub@gmail.com
License: LICENSE
Keywords: pytorch cnn layers
Platform: UNKNOWN
Requires-Python: >=3.7
License-File: LICENSE
Requires-Dist: pytorch-lightning (>=1.2.0)
Requires-Dist: torchvision
Requires-Dist: varname
